comlib/__init__.py
comlib/comlib.py
comlib-0.4.2.dist-info/DESCRIPTION.rst
comlib-0.4.2.dist-info/METADATA
comlib-0.4.2.dist-info/RECORD
comlib-0.4.2.dist-info/WHEEL
comlib-0.4.2.dist-info/metadata.json
comlib-0.4.2.dist-info/top_level.txt
