Metadata-Version: 2.0
Name: comlib
Version: 0.4.2
Summary: Randomization and communities
Home-page: UNKNOWN
Author: UNKNOWN
Author-email: sergey-vorobyof@mail.ru
License: UNKNOWN
Platform: UNKNOWN
